stupify/__init__.py
stupify/_about.py
stupify-0.0.1.dev1.dist-info/COPYING.LESSER.md
stupify-0.0.1.dev1.dist-info/COPYING.md
stupify-0.0.1.dev1.dist-info/METADATA
stupify-0.0.1.dev1.dist-info/WHEEL
stupify-0.0.1.dev1.dist-info/top_level.txt
stupify-0.0.1.dev1.dist-info/RECORD
